[
  {
    "name": "ボルノレキサント",
    "brand": "ボルズィ",
    "category": "睡眠薬",
    "class": "オレキシン受容体拮抗薬",
    "action_type": "催眠作用・覚醒抑制作用",
    "mechanism": "オレキシン1/2受容体を遮断し、覚醒シグナルを選択的に抑制して自然な眠りを促す",
    "potency": "換算なし（オレキシン系）",
    "efficacy_star": 4,
    "placebo_onset": "入眠時間−10.6分",
    "placebo_sleep": "中途覚醒−12.3分",
    "NNT": 5,
    "duration_hours": "4〜6時間（t1/2約2時間・持越し少）",
    "guideline_rank": "持越しが最も少ないDORA。高齢者・翌朝の眠気が問題になる患者に",
    "evidence": "第III相試験 301試験（2025年承認）",
    "caution": "翌朝の持越しが最も少ないDORA。強力なCYP3A阻害薬（イトラコナゾール等）との併用禁忌"
  },
  {
    "name": "ダリドレキサント",
    "brand": "クービビック",
    "category": "睡眠薬",
    "class": "オレキシン受容体拮抗薬",
    "action_type": "催眠作用・覚醒抑制作用",
    "mechanism": "オレキシン1/2受容体を選択的に遮断し、覚醒維持シグナルを遮断して入眠・睡眠維持を改善",
    "potency": "換算なし（オレキシン系）",
    "efficacy_star": 4,
    "placebo_onset": "入眠時間−11.4分",
    "placebo_sleep": "中途覚醒−22.8分",
    "NNT": 4.2,
    "duration_hours": "6〜8時間",
    "guideline_rank": "中途覚醒改善に優れる。CYP3A4阻害薬がない患者に適する",
    "evidence": "Lancet Neurology 2022（HERALDトライアル PMID:35065036）",
    "caution": "依存性は低い。CYP3A4基質のため一部薬との相互作用に注意"
  },
  {
    "name": "レンボレキサント",
    "brand": "デエビゴ",
    "category": "睡眠薬",
    "class": "オレキシン受容体拮抗薬",
    "action_type": "催眠作用・覚醒抑制作用",
    "mechanism": "オレキシン1/2受容体を強力に遮断。ゾルピデムと比較して翌朝の認知・運動機能への影響が少ない",
    "potency": "換算なし（オレキシン系）",
    "efficacy_star": 5,
    "placebo_onset": "入眠時間−10.1分",
    "placebo_sleep": "中途覚醒−17.5分",
    "NNT": 3.2,
    "duration_hours": "6〜8時間",
    "guideline_rank": "入眠・維持両方に有効。翌朝の認知・運動機能への影響が少ない",
    "evidence": "SUNRISE 1/2試験（Lancet Neurology 2019 PMID:31880796）",
    "evidence_url": "https://pubmed.ncbi.nlm.nih.gov/31880796/",
    "caution": "依存性は低い。CYP3A4阻害薬との併用に注意"
  },
  {
    "name": "スボレキサント",
    "brand": "ベルソムラ",
    "category": "睡眠薬",
    "class": "オレキシン受容体拮抗薬",
    "action_type": "催眠作用・覚醒抑制作用",
    "mechanism": "オレキシン1/2受容体を遮断し、過剰な覚醒状態をオフにすることで睡眠への移行を助ける",
    "potency": "換算なし（オレキシン系）",
    "efficacy_star": 4,
    "placebo_onset": "入眠時間−5.6分",
    "placebo_sleep": "中途覚醒−16.6分",
    "NNT": 4.5,
    "duration_hours": "7〜9時間",
    "guideline_rank": "最初に登場したオレキシン拮抗薬。依存性が低く長期使用に適する",
    "evidence": "Phase 3 Pooled Analysis（PMC4990943）",
    "caution": "翌日の眠気に注意。依存性は低い"
  },
  {
    "name": "ラメルテオン",
    "brand": "ロゼレム",
    "category": "睡眠薬",
    "class": "メラトニン受容体作動薬",
    "action_type": "概日リズム調節・入眠促進作用",
    "mechanism": "MT1/MT2メラトニン受容体に高親和性で結合し、松果体のメラトニン様作用で概日リズムを調整して入眠を促す",
    "potency": "換算なし（メラトニン系）",
    "efficacy_star": 2,
    "placebo_onset": "入眠時間−15.7分",
    "placebo_sleep": "総睡眠+19分",
    "NNT": 9.2,
    "duration_hours": "入眠改善（持続効果は限定的）",
    "guideline_rank": "依存性・翌日持越しがほぼなし。高齢者・依存症リスクが高い患者に",
    "evidence": "Zammit et al., JCSM 2007（PMC1978328）",
    "caution": "依存性・乱用リスクなし。効果は比較的弱め"
  },
  {
    "name": "エスゾピクロン",
    "brand": "ルネスタ",
    "category": "睡眠薬",
    "class": "非ベンゾジアゼピン系",
    "action_type": "催眠作用・鎮静作用",
    "mechanism": "GABA-A受容体のBZD結合部位に結合し、GABA作用を増強。ゾルピデムより広いサブユニット選択性",
    "potency": "1mg ≑ DZP 5mg",
    "efficacy_star": 4,
    "placebo_onset": "入眠時間−15分",
    "placebo_sleep": "睡眠効率+6%",
    "NNT": 4.1,
    "duration_hours": "6〜9時間",
    "guideline_rank": "入眠・睡眠維持ともに有効。BZよりやや依存性が低い非ベンゾ系",
    "evidence": "JCSM 2008（PMID:18595435）; PMDA審査資料",
    "caution": "苦味の副作用が多い。依存性に注意"
  },
  {
    "name": "ゾルピデム",
    "brand": "マイスリー",
    "category": "睡眠薬",
    "class": "非ベンゾジアゼピン系",
    "action_type": "催眠作用（入眠促進）",
    "mechanism": "GABA-A受容体のω1サブユニット（BZ1受容体）に選択的に結合し、Cl⁻チャネルの開口を促進して神経抑制を増強",
    "potency": "5mg ≑ DZP 5mg",
    "efficacy_star": 4,
    "placebo_onset": "データなし",
    "placebo_sleep": "中途覚醒−19分 / 総睡眠+36分",
    "NNT": 3.8,
    "duration_hours": "5〜8時間",
    "guideline_rank": "入眠障害に特化。短時間作用で翌朝への持越しが少ない非ベンゾ系",
    "evidence": "Morin et al., Sleep 2012（PMC3466802）",
    "caution": "依存性・反跳性不眠に注意。高齢者は転倒リスクあり"
  },
  {
    "name": "トリアゾラム",
    "brand": "ハルシオン",
    "category": "睡眠薬",
    "class": "ベンゾジアゼピン系",
    "action_type": "催眠作用（強力な短時間型）",
    "mechanism": "GABA-A受容体のBZD結合部位に高親和性で結合。短時間型で強力な催眠効果を示すが、健忘リスクが高い",
    "potency": "0.25mg ≑ DZP 5mg",
    "efficacy_star": 3,
    "placebo_onset": "入眠時間−10分",
    "placebo_sleep": "データなし",
    "NNT": 5.5,
    "duration_hours": "3〜5時間（短時間型）",
    "guideline_rank": "超短時間型BZ。入眠困難のみ・健忘リスクがあるため短期使用限定",
    "evidence": "AASM臨床ガイドライン（J Clin Sleep Med 2017）",
    "caution": "強い依存性・健忘・反跳性不眠。長期使用は非推奨"
  },
  {
    "name": "ブロチゾラム",
    "brand": "レンドルミン",
    "category": "睡眠薬",
    "class": "ベンゾジアゼピン系",
    "action_type": "鎮静・催眠・抗不安・筋弛緩作用",
    "mechanism": "GABA-A受容体のBZD結合部位に結合し、GABAのCl⁻チャネル開口作用を増強。全サブタイプに作用するため筋弛緩・抗不安効果も伴う",
    "potency": "0.25mg ≑ DZP 5mg",
    "efficacy_star": 3,
    "placebo_onset": "入眠時間−15分（国内データ）",
    "placebo_sleep": "中途覚醒−20分 / 総睡眠+40分",
    "NNT": 4.5,
    "duration_hours": "6〜12時間",
    "guideline_rank": "第一選択が使えない際の代替薬",
    "evidence": "国内添付文書（JAPIC）",
    "caution": "依存性・反跳性不眠・記憶障害に注意"
  },
  {
    "name": "ニトラゼパム",
    "brand": "ベンザリン",
    "category": "睡眠薬",
    "class": "ベンゾジアゼピン系",
    "action_type": "鎮静・催眠・抗てんかん作用",
    "mechanism": "GABA-A受容体のBZD結合部位に結合しGABA作用を増強。長時間型のため翌日への持ち越しに注意",
    "potency": "5mg ≑ DZP 5mg",
    "efficacy_star": 3,
    "placebo_onset": "入眠時間−18分（国内データ）",
    "placebo_sleep": "総睡眠+50分（国内データ）",
    "NNT": "未算出（国内エビデンス限定）",
    "duration_hours": "18〜38時間（長時間型）",
    "guideline_rank": "中等度の睡眠維持障害に。筋弛緩・抗不安作用もあり（BZ系）",
    "evidence": "国内添付文書（JAPIC）",
    "caution": "翌日の眠気・依存性・筋弛緩作用に注意"
  },
  {
    "name": "エスシタロプラム",
    "brand": "レクサプロ",
    "category": "抗不安薬",
    "class": "SSRI",
    "action_type": "抗不安作用・抗うつ作用",
    "mechanism": "SERT選択性が最も高いSSRI。アロステリック部位にも結合し、効果と忍容性のバランスが良好",
    "potency": "10mg ≑ IMP 100mg",
    "efficacy_star": 5,
    "placebo_onset": "HAM-A −3.9点",
    "placebo_sleep": "治療反応率+20%",
    "NNT": 3.1,
    "duration_hours": "効果発現まで2〜4週間",
    "guideline_rank": "うつ病・GADの第一選択。相互作用が少なく忍容性が高い",
    "evidence": "Davidson et al., Depr Anxiety 2004（PMID:15274172）",
    "caution": "QT延長リスク。導入初期に不安が一時的に増強することあり"
  },
  {
    "name": "パロキセチン",
    "brand": "パキシル",
    "category": "抗不安薬",
    "class": "SSRI",
    "action_type": "抗不安作用・抗うつ作用",
    "mechanism": "セロトニントランスポーター（SERT）を選択的に阻害し、シナプス間隙のセロトニン濃度を増加させて不安・抑うつを改善",
    "potency": "20mg ≑ IMP 100mg",
    "efficacy_star": 5,
    "placebo_onset": "HAM-A −3.2点",
    "placebo_sleep": "治療反応率+16〜22%",
    "NNT": 2.9,
    "duration_hours": "効果発現まで2〜4週間",
    "guideline_rank": "うつ病・パニック・社交不安・PTSD。中断症状に注意",
    "evidence": "Rickels et al., Am J Psychiatry 2003（PMID:12668365）",
    "caution": "中断症状に注意。性機能障害・体重増加の副作用あり"
  },
  {
    "name": "デュロキセチン",
    "brand": "サインバルタ",
    "category": "抗不安薬",
    "class": "SNRI",
    "action_type": "抗不安作用・抗うつ作用・鎮痛補助作用",
    "mechanism": "SERT・NET（ノルエピネフリントランスポーター）の両方を阻害。下行性疼痛抑制系への作用で慢性疼痛にも有効",
    "potency": "40mg ≑ IMP 100mg",
    "efficacy_star": 4,
    "placebo_onset": "HAM-A −4.4点",
    "placebo_sleep": "治療反応率+27%",
    "NNT": 3.7,
    "duration_hours": "効果発現まで2〜4週間",
    "guideline_rank": "うつ病・GAD・糖尿病性神経障害・慢性腰痛にも適応",
    "evidence": "Hartford et al., Int Clin Psychopharmacol 2007（PMID:17311303）",
    "caution": "嘔気・血圧上昇。急激な中断は避ける。抗うつ薬・神経障害性疼痛にも使用"
  },
  {
    "name": "タンドスピロン",
    "brand": "セディール",
    "category": "抗不安薬",
    "class": "セロトニン1A受容体作動薬",
    "action_type": "抗不安作用（弱め）",
    "mechanism": "5-HT1A受容体の部分作動薬。縫線核のオートレセプターと海馬のポストシナプス受容体に作用し、セロトニン神経系を調整して不安を緩和",
    "potency": "換算なし（5-HT1A系）",
    "efficacy_star": 2,
    "placebo_onset": "HAM-A −1.5点（国内データ）",
    "placebo_sleep": "治療反応率+12%（国内データ）",
    "NNT": 10,
    "duration_hours": "効果発現まで1〜2週間",
    "guideline_rank": "依存性なし・緩やかな効果。長期維持・BZ離脱後の不安に",
    "evidence": "国内臨床試験データ（添付文書）",
    "caution": "依存性なし。効果発現が遅い。急性不安には不向き"
  },
  {
    "name": "ロラゼパム",
    "brand": "ワイパックス",
    "category": "抗不安薬",
    "class": "ベンゾジアゼピン系",
    "action_type": "抗不安作用・鎮静作用・催眠作用",
    "mechanism": "GABA-A受容体のBZD結合部位に結合しGABA作用を増強。肝代謝での薬物相互作用が少なく（グルクロン酸抱合）、高齢者・肝疾患患者に比較的安全",
    "potency": "1mg ≑ DZP 5mg",
    "efficacy_star": 4,
    "placebo_onset": "HAM-A −2.7点",
    "placebo_sleep": "治療反応率+24%（GAD）",
    "NNT": 4,
    "duration_hours": "6〜12時間",
    "guideline_rank": "即効性・中間作用。肝障害合併患者にも使いやすいBZ系",
    "evidence": "Fresquet et al., 2000（PMID:10676820）",
    "caution": "依存性・鎮静・記憶障害。長期使用非推奨"
  },
  {
    "name": "アルプラゾラム",
    "brand": "コンスタン／ソラナックス",
    "category": "抗不安薬",
    "class": "ベンゾジアゼピン系",
    "action_type": "抗不安作用・鎮静作用・催眠作用",
    "mechanism": "GABA-A受容体のBZD結合部位に結合しGABA作用を増強。即効性があり急性不安に有効だが依存性が高い",
    "potency": "0.5mg ≑ DZP 5mg",
    "efficacy_star": 4,
    "placebo_onset": "HAM-A −2.5点",
    "placebo_sleep": "治療反応率+22%（GAD）",
    "NNT": 3.9,
    "duration_hours": "6〜12時間",
    "guideline_rank": "即効性が高くパニック発作の頓服に。依存性があり長期連用は避ける",
    "evidence": "プレガバリン比較試験（PMID:16143734）",
    "caution": "依存性が高い。長期使用は推奨されない"
  },
  {
    "name": "クロナゼパム",
    "brand": "リボトリール／ランドセン",
    "category": "抗不安薬",
    "class": "ベンゾジアゼピン系",
    "action_type": "抗不安作用・抗てんかん作用・筋弛緩作用",
    "mechanism": "GABA-A受容体のBZD結合部位に結合。長時間型で安定した抗不安・抗てんかん効果を発揮",
    "potency": "0.5mg ≑ DZP 5mg",
    "efficacy_star": 4,
    "placebo_onset": "発作消失率+25%",
    "placebo_sleep": "治療反応率+30%（パニック障害）",
    "NNT": 4.1,
    "duration_hours": "18〜50時間（長時間型）",
    "guideline_rank": "パニック障害の維持療法。抗けいれん作用を兼ねる",
    "evidence": "Pande et al., J Clin Psychiatry 2000（PMID:10520979）",
    "caution": "鎮静・依存性・長期蓄積に注意。抗てんかん薬としても使用（ミオクロニー発作等）"
  },
  {
    "name": "エチゾラム",
    "brand": "デパス",
    "category": "抗不安薬",
    "class": "チエノジアゼピン系",
    "action_type": "抗不安作用・鎮静作用・筋弛緩作用",
    "mechanism": "GABA-A受容体のBZD結合部位に結合（チエノジアゼピン骨格）。抗不安・鎮静・筋弛緩・催眠作用を持つ",
    "potency": "1.5mg ≑ DZP 5mg",
    "efficacy_star": 3,
    "placebo_onset": "HAM-A −2.0点（国内データ）",
    "placebo_sleep": "治療反応率+20%（国内データ）",
    "NNT": 5,
    "duration_hours": "6〜12時間",
    "guideline_rank": "日本で広く使用される短時間作用BZ。不眠合併の不安症状に",
    "evidence": "国内使用実績（国際的RCTデータ限定的）",
    "caution": "依存性・乱用リスク高い。2016年より向精神薬指定"
  },
  {
    "name": "ハロペリドール",
    "brand": "セレネース",
    "category": "抗精神病薬（定型）",
    "class": "定型抗精神病薬（高力価）",
    "action_type": "抗精神病作用・強力鎮静作用",
    "mechanism": "D2受容体を強力に遮断し、中脳辺縁系の過剰なドパミン神経伝達を抑制。陽性症状（幻覚・妄想）に有効",
    "potency": "2mg ≑ CPZ 100mg",
    "efficacy_star": 4,
    "placebo_onset": "PANSS −9.6点（プラセボ比）",
    "placebo_sleep": "治療反応率+40%",
    "NNT": 3.5,
    "duration_hours": "8〜24時間（半減期12〜35時間）",
    "guideline_rank": "幻覚・妄想に強力。急性期の興奮・せん妄に筋注でも使用可",
    "evidence": "Davis et al., Schizophr Bull 2003; Leucht et al., Lancet 2013（PMID:23810019）",
    "caution": "錐体外路症状（EPS）・遅発性ジスキネジアのリスクが高い。高プロラクチン血症。デポ製剤（ハロペリドールデカノアート）もあり",
    "positive_symptoms": "幻覚・妄想への有効性★★★★★（D2強遮断）",
    "negative_symptoms": "改善乏しい・錐体外路症状で悪化しやすい"
  },
  {
    "name": "フルフェナジン",
    "brand": "フルメジン",
    "category": "抗精神病薬（定型）",
    "class": "定型抗精神病薬（高力価）",
    "action_type": "抗精神病作用",
    "mechanism": "D2受容体を強力に遮断するフェノチアジン系高力価薬。デポ注射製剤による長時間作用が特徴",
    "potency": "2mg ≑ CPZ 100mg",
    "efficacy_star": 3,
    "placebo_onset": "PANSS −9.0点（プラセボ比）",
    "placebo_sleep": "治療反応率+38%",
    "NNT": 3.6,
    "duration_hours": "12〜24時間（デポ：2〜4週間）",
    "guideline_rank": "デポ製剤あり。服薬アドヒアランスが低い患者の維持療法に",
    "evidence": "国内添付文書；Cochrane Review（Marques et al. 2004）",
    "caution": "EPSリスクが高い。デポ注射製剤（フルデカシン）は長時間作用型で服薬アドヒアランス改善に使用",
    "positive_symptoms": "幻覚・妄想★★★★（デポ製剤で継続率高）",
    "negative_symptoms": "改善不良・EPS頻度高い"
  },
  {
    "name": "クロルプロマジン",
    "brand": "コントミン",
    "category": "抗精神病薬（定型）",
    "class": "定型抗精神病薬（低力価）",
    "action_type": "抗精神病作用・鎮静作用・制吐作用",
    "mechanism": "D2・5-HT2A・α1・H1・M1など多受容体を遮断。鎮静・制吐作用が強く、歴史的に最初の抗精神病薬",
    "potency": "100mg（CPZ換算基準薬）",
    "efficacy_star": 3,
    "placebo_onset": "BPRS −7.0点（プラセボ比）",
    "placebo_sleep": "治療反応率+35%",
    "NNT": 3.8,
    "duration_hours": "12〜24時間",
    "guideline_rank": "鎮静が主目的。強い興奮・不眠合併例に",
    "evidence": "Cochrane Review（Adams et al. 2014）",
    "caution": "鎮静が強い。低血圧・抗コリン副作用・光線過敏・肝障害。EPSは高力価定型薬より少ない",
    "positive_symptoms": "陽性症状に有効★★★（広域D2遮断）",
    "negative_symptoms": "改善乏しい・鎮静が主"
  },
  {
    "name": "スルピリド",
    "brand": "ドグマチール",
    "category": "抗精神病薬（定型）",
    "class": "定型抗精神病薬（低力価）",
    "action_type": "抗精神病・胃潰瘍・抗うつ（用量依存）",
    "mechanism": "D2受容体遮断（辺縁系選択性）。低用量では前シナプスD2遮断でドパミン遊離促進→抗うつ・陰性症状改善",
    "positive_symptoms": "陽性症状★★★（低用量では陰性症状も）",
    "negative_symptoms": "低用量で改善★★★（D2弱遮断・プロラクチン↑）",
    "placebo_onset": "BPRS改善 プラセボ比−7〜9点",
    "placebo_sleep": "治療反応率 55〜65%",
    "NNT": 5.5,
    "efficacy_star": 3,
    "duration_hours": "8〜12時間（t1/2 約8h）",
    "guideline_rank": "低用量で陰性症状・抑うつ・胃潰瘍にも適応。高用量で陽性症状",
    "evidence": "Cochrane review 2002（PMID:10796605）",
    "evidence_url": "https://pubmed.ncbi.nlm.nih.gov/10796605/",
    "caution": "プロラクチン↑顕著（無月経・乳汁分泌）。腎排泄のため腎機能低下例は減量。高用量でEPS"
  },
  {
    "name": "レボメプロマジン",
    "brand": "ヒルナミン・レボトミン",
    "category": "抗精神病薬（定型）",
    "class": "定型抗精神病薬（低力価）",
    "action_type": "鎮静・抗精神病",
    "mechanism": "D2・H1・α1・M受容体を広域遮断。強力な鎮静作用。緩和ケアでの制吐・鎮静にも使用",
    "positive_symptoms": "陽性症状★★★（広域遮断・鎮静）",
    "negative_symptoms": "改善乏しい（鎮静効果が主）",
    "placebo_onset": "BPRS改善 プラセボ比−6〜8点",
    "placebo_sleep": "治療反応率 50〜60%",
    "NNT": 6,
    "efficacy_star": 3,
    "duration_hours": "12〜24時間（t1/2 15〜30h）",
    "guideline_rank": "強力な鎮静が必要な難治性不眠・緩和ケア場面に",
    "evidence": "添付文書・臨床経験",
    "evidence_url": null,
    "caution": "強い鎮静・起立性低血圧・口渇。QT延長リスク。抗コリン作用あり"
  },
  {
    "name": "クロザピン",
    "brand": "クロザリル",
    "category": "抗精神病薬（非定型）",
    "class": "非定型抗精神病薬（MARTA）",
    "action_type": "治療抵抗性統合失調症治療薬",
    "mechanism": "D1-4・5-HT2A/2C・H1・M・α遮断の広域プロファイル。治療抵抗性に唯一エビデンスある薬剤",
    "positive_symptoms": "治療抵抗性幻覚・妄想★★★★★",
    "negative_symptoms": "陰性症状★★★★（最も優れたエビデンス）",
    "placebo_onset": "BPRS改善 他剤無効例の30〜60%が反応",
    "placebo_sleep": "治療反応率（無効例から）30〜60%",
    "NNT": 3,
    "efficacy_star": 5,
    "duration_hours": "12〜16時間（t1/2 12h）",
    "guideline_rank": "2剤以上の抗精神病薬が無効な治療抵抗性統合失調症に限定使用",
    "evidence": "Kane JM et al. Arch Gen Psychiatry 1988（PMID:3046553）",
    "evidence_url": "https://pubmed.ncbi.nlm.nih.gov/3046553/",
    "caution": "無顆粒球症（1〜2%）のため定期血液検査必須（CPMS登録）。体重増加・糖尿病リスク高。過鎮静・流涎"
  },
  {
    "name": "オランザピン",
    "brand": "ジプレキサ",
    "category": "抗精神病薬（非定型）",
    "class": "非定型抗精神病薬（MARTA）",
    "action_type": "抗精神病作用・気分安定作用・強力鎮静作用",
    "mechanism": "D2・5-HT2A・H1・M1・α1など多受容体に幅広く拮抗（MARTA）。鎮静・食欲促進作用が強く、代謝への影響が大きい",
    "potency": "4mg ≑ CPZ 100mg",
    "efficacy_star": 5,
    "placebo_onset": "PANSS −11.5点（プラセボ比）",
    "placebo_sleep": "治療反応率+42%",
    "NNT": 3.5,
    "duration_hours": "24時間（半減期21〜54時間）",
    "guideline_rank": "陽性・陰性症状ともに有効。体重増加・代謝リスクを許容できる例に",
    "evidence": "Leucht et al., Lancet 2013; CATIE試験（PMID:16172203）",
    "caution": "体重増加・血糖上昇・高脂血症が著明（代謝症候群リスク）。鎮静が強い。効果の高さはトップクラス",
    "positive_symptoms": "陽性症状★★★★",
    "negative_symptoms": "陰性症状★★★★（多元受容体遮断）"
  },
  {
    "name": "クエチアピン",
    "brand": "セロクエル",
    "category": "抗精神病薬（非定型）",
    "class": "非定型抗精神病薬（MARTA）",
    "action_type": "抗精神病作用・抗不安作用・催眠作用（低用量）",
    "mechanism": "D2・5-HT2A・H1・α1など多受容体拮抗（MARTA）。D2遮断は弱いため錐体外路症状が少なく、低用量で不眠・不安にも使用",
    "potency": "100mg ≑ CPZ 100mg",
    "efficacy_star": 4,
    "placebo_onset": "PANSS −10.0点（プラセボ比）",
    "placebo_sleep": "治療反応率+35%",
    "NNT": 4.5,
    "duration_hours": "12〜24時間（XR製剤で1日1回）",
    "guideline_rank": "鎮静・睡眠障害合併例に。代謝影響はオランザピンより少ない",
    "evidence": "Leucht et al., Lancet 2013; BOLDER試験（双極性障害うつ）",
    "caution": "D2遮断は弱くEPS少ない。体重増加・眠気が主な副作用。低用量で不眠・不安への適応外使用あり",
    "positive_symptoms": "陽性症状★★★",
    "negative_symptoms": "陰性症状★★★・抑うつにも効果"
  },
  {
    "name": "アセナピン",
    "brand": "シクレスト",
    "category": "抗精神病薬（非定型）",
    "class": "非定型抗精神病薬（MARTA）",
    "action_type": "抗精神病（統合失調症・双極性障害そう状態）",
    "mechanism": "D2・5-HT2A/2C・α2・H1受容体を遮断。舌下投与（嚥下不可）で速やかな吸収",
    "positive_symptoms": "陽性症状★★★★",
    "negative_symptoms": "陰性症状★★★（多受容体プロファイル）",
    "placebo_onset": "PANSS改善 プラセボ比−12〜16点",
    "placebo_sleep": "治療反応率 60〜70%",
    "NNT": 5,
    "efficacy_star": 4,
    "duration_hours": "12時間（t1/2 24h・1日2回）",
    "guideline_rank": "舌下投与で剤形の選択肢が増える。体重増加は中程度",
    "evidence": "Potkin SG et al. J Clin Psychiatry 2007（PMID:17960962）",
    "evidence_url": "https://pubmed.ncbi.nlm.nih.gov/17960962/",
    "caution": "舌下投与必須（飲み込むと生体内利用率<2%）。口腔内感覚鈍麻。体重増加あり"
  },
  {
    "name": "リスペリドン",
    "brand": "リスパダール",
    "category": "抗精神病薬（非定型）",
    "class": "非定型抗精神病薬（SDA）",
    "action_type": "抗精神病作用（陽性・陰性症状改善）",
    "mechanism": "D2受容体遮断＋5-HT2A受容体遮断（SDA：セロトニン・ドパミン拮抗薬）。低用量では5-HT2A遮断が優位でEPSが少ない",
    "potency": "2mg ≑ CPZ 100mg",
    "efficacy_star": 4,
    "placebo_onset": "PANSS −10.2点（プラセボ比）",
    "placebo_sleep": "治療反応率+38%",
    "NNT": 4,
    "duration_hours": "12〜24時間",
    "guideline_rank": "非定型の基本薬。幻覚・妄想に有効で剤形豊富（内服・液・注射・デポ）",
    "evidence": "Leucht et al., Lancet 2013（PMID:23810019）; Marder et al., 2003",
    "caution": "高用量でEPS・高プロラクチン血症。低用量では忍容性良好。デポ注射製剤あり（リスパダールコンスタ）",
    "positive_symptoms": "幻覚・妄想★★★★（D2/5-HT2A遮断）",
    "negative_symptoms": "中等度改善★★★（5-HT2A拮抗）"
  },
  {
    "name": "パリペリドン",
    "brand": "インヴェガ",
    "category": "抗精神病薬（非定型）",
    "class": "非定型抗精神病薬（SDA）",
    "action_type": "抗精神病作用（陽性・陰性症状改善）",
    "mechanism": "リスペリドンの活性代謝物（9-OH-リスペリドン）。D2・5-HT2A受容体拮抗（SDA）。月1回・3ヶ月1回注射製剤が利便性高い",
    "potency": "2.5mg ≑ CPZ 100mg",
    "efficacy_star": 4,
    "placebo_onset": "PANSS −9.8点（プラセボ比）",
    "placebo_sleep": "治療反応率+37%",
    "NNT": 4.2,
    "duration_hours": "24時間（XR錠）；月1回デポあり（ゼプリオン）",
    "guideline_rank": "リスペリドンの活性代謝物。月1回注射（デポ）が維持療法に有用",
    "evidence": "Kane et al., J Clin Psychopharmacol 2007; デポ製剤（ゼプリオン）長期試験",
    "caution": "高プロラクチン血症。リスペリドンの活性代謝物で効果・副作用が類似。月1回・3ヶ月1回注射製剤が服薬管理に有用",
    "positive_symptoms": "幻覚・妄想★★★★（活性代謝物）",
    "negative_symptoms": "中等度改善★★★"
  },
  {
    "name": "ルラシドン",
    "brand": "ラツーダ",
    "category": "抗精神病薬（非定型）",
    "class": "非定型抗精神病薬（SDA）",
    "action_type": "抗精神病・認知機能改善",
    "mechanism": "D2・5-HT2A遮断 + 5-HT7遮断により認知機能・抑うつ改善。代謝への影響が少ない",
    "positive_symptoms": "陽性症状★★★★",
    "negative_symptoms": "陰性症状★★★・認知機能改善",
    "placebo_onset": "PANSS改善 プラセボ比−14〜18点",
    "placebo_sleep": "治療反応率 65〜75%",
    "NNT": 4,
    "efficacy_star": 4,
    "duration_hours": "24時間（t1/2 18h・1日1回）",
    "guideline_rank": "代謝への影響が少ない。認知機能改善・食後投与が必須",
    "evidence": "Loebel A et al. J Clin Psychiatry 2013（PMID:23541189）",
    "evidence_url": "https://pubmed.ncbi.nlm.nih.gov/23541189/",
    "caution": "食後（350kcal以上）投与必須（空腹時は血中濃度1/2）。CYP3A4基質。体重・血糖への影響少ない"
  },
  {
    "name": "ブロナンセリン",
    "brand": "ロナセン",
    "category": "抗精神病薬（非定型）",
    "class": "非定型抗精神病薬（SDA）",
    "action_type": "抗精神病（D2高選択性・EPS少）",
    "mechanism": "D2・D3受容体を高選択的に遮断。5-HT2A遮断でEPS軽減。貼付剤（ロナセンテープ）あり",
    "positive_symptoms": "幻覚・妄想★★★★（高選択D2遮断）",
    "negative_symptoms": "中等度改善★★★（5-HT2A遮断）",
    "placebo_onset": "PANSS改善 プラセボ比−12〜15点",
    "placebo_sleep": "治療反応率 60〜70%",
    "NNT": 4.5,
    "efficacy_star": 4,
    "duration_hours": "12〜24時間（貼付剤24時間）",
    "guideline_rank": "嚥下困難例にテープ剤が有用。EPSは中程度",
    "evidence": "Kane JM et al. J Clin Psychiatry 2015（PMID:25919841）",
    "evidence_url": null,
    "caution": "食後投与で吸収↑（空腹時は効果減弱）。テープは皮膚刺激に注意。EPS中程度"
  },
  {
    "name": "ペロスピロン",
    "brand": "ルーラン",
    "category": "抗精神病薬（非定型）",
    "class": "非定型抗精神病薬（SDA）",
    "action_type": "抗精神病・抗不安",
    "mechanism": "D2・5-HT2A遮断 + 5-HT1A部分作動。5-HT1A作動により不安・陰性症状・認知機能改善に寄与",
    "positive_symptoms": "陽性症状★★★",
    "negative_symptoms": "陰性症状★★★（5-HT1A部分作動）",
    "placebo_onset": "PANSS改善 プラセボ比−10〜13点",
    "placebo_sleep": "治療反応率 55〜65%",
    "NNT": 5,
    "efficacy_star": 3,
    "duration_hours": "8〜12時間（t1/2 約3h・1日3回）",
    "guideline_rank": "5-HT1A作動で不安・抑うつ合併例に。1日3回服用が欠点",
    "evidence": "Murasaki M et al. Psychiatry Clin Neurosci 2007（PMID:17316357）",
    "evidence_url": null,
    "caution": "食後投与必須（空腹時は吸収不良）。1日3回服用で服薬アドヒアランス↓のリスク"
  },
  {
    "name": "アリピプラゾール",
    "brand": "エビリファイ",
    "category": "抗精神病薬（非定型）",
    "class": "非定型抗精神病薬（DSS）",
    "action_type": "抗精神病作用・抗うつ補助作用",
    "mechanism": "D2受容体部分作動薬（過活動を抑え、低活動を補う）＋5-HT1A部分作動薬・5-HT2A拮抗（DSS）。体重・代謝への影響が少ない",
    "potency": "6.5mg ≑ CPZ 100mg",
    "efficacy_star": 4,
    "placebo_onset": "PANSS −8.5点（プラセボ比）",
    "placebo_sleep": "治療反応率+28%",
    "NNT": 5,
    "duration_hours": "24時間（半減期75〜94時間）",
    "guideline_rank": "代謝副作用が少ない。体重増加・QT延長を避けたい患者に",
    "evidence": "Leucht et al., Lancet 2013; Berman et al., CNS Spectr 2007（うつ病補助）",
    "caution": "アカシジア（静座不能）が比較的多い。体重・代謝への影響は少ない。うつ病補助療法・抗うつ薬としても使用",
    "positive_symptoms": "陽性症状★★★★（D2部分作動）",
    "negative_symptoms": "陰性症状★★★（D2部分作動・5-HT1A作動）"
  },
  {
    "name": "カリプラジン",
    "brand": "レアルダ",
    "category": "抗精神病薬（非定型）",
    "class": "非定型抗精神病薬（DSS）",
    "action_type": "抗精神病・陰性症状改善",
    "mechanism": "D3受容体優先的部分作動（D3/D2比 10:1）。陰性症状・認知機能へのエビデンスが最強クラス",
    "positive_symptoms": "陽性症状★★★★（D3/D2部分作動）",
    "negative_symptoms": "陰性症状★★★★★（D3優先作動で最強エビデンス）",
    "placebo_onset": "PANSS改善 プラセボ比−15〜20点",
    "placebo_sleep": "陰性症状反応率 45〜60%（NSA-16評価）",
    "NNT": 4,
    "efficacy_star": 5,
    "duration_hours": "24時間（活性代謝物t1/2 1〜3週）",
    "guideline_rank": "陰性症状が前景の統合失調症に最もエビデンスが強い",
    "evidence": "Németh G et al. Lancet 2017（PMID:28185672）",
    "evidence_url": "https://pubmed.ncbi.nlm.nih.gov/28185672/",
    "caution": "活性代謝物の半減期が長く（1〜3週）、副作用発現が遅れることがある。アカシジアに注意"
  },
  {
    "name": "ブレクスピプラゾール",
    "brand": "レキサルティ",
    "category": "抗精神病薬（非定型）",
    "class": "非定型抗精神病薬（DSS）",
    "action_type": "抗うつ補助作用・抗精神病作用",
    "mechanism": "D2受容体部分作動薬（アリピプラゾールより安定した部分作動活性）＋5-HT1A部分作動薬・5-HT2A強力拮抗。アカシジアが少なめ",
    "potency": "3mg ≑ CPZ 100mg",
    "efficacy_star": 3,
    "placebo_onset": "MADRS −3.0点（うつ病補助；プラセボ比）",
    "placebo_sleep": "治療反応率+15%（うつ病補助）",
    "NNT": 8,
    "duration_hours": "24時間（半減期91時間）",
    "guideline_rank": "陰性症状・抑うつへの効果。忍容性に優れ認知機能改善の期待",
    "evidence": "Thase et al., J Clin Psychiatry 2015; Kane et al., J Clin Psychiatry 2015（統合失調症）",
    "caution": "アカシジアはアリピプラゾールより少ない。体重増加はやや多め。日本でうつ病補助適応あり",
    "positive_symptoms": "陽性症状★★★（D2部分作動）",
    "negative_symptoms": "陰性症状★★★（5-HT1A強作動）"
  },
  {
    "name": "ズラノロン",
    "brand": "ザズベイ",
    "category": "抗うつ薬",
    "class": "ニューロステロイド GABAA-PAM",
    "action_type": "GABAA受容体ポジティブアロステリックモジュレーター",
    "mechanism": "シナプス内外のGABAA受容体ポジティブアロステリックモジュレーター（PAM）。\nGABAによる抑制性電流を増強し神経活動を調節。モノアミン系とは異なる機序で速やかな抗うつ効果を発揮。",
    "efficacy_star": 4,
    "placebo_onset": "HAMD −1.8点（Day 15、プラセボ比）",
    "placebo_sleep": "治療反応率 +17%（プラセボ比、Day 15）",
    "NNT": 5.9,
    "onset_time": "投与3日以内",
    "duration_hours": "半減期 約14時間（14日間投与で効果持続）",
    "guideline_rank": "国内新薬につき未策定（2025年承認）",
    "evidence": "Clayton AH, et al. Am J Psychiatry. 2023. PMID: 37132201",
    "evidence_url": "https://pubmed.ncbi.nlm.nih.gov/37132201/",
    "caution": "主な副作用は傾眠(20.0%)、めまい(12.6%)。自殺念慮・企図のリスクに注意。妊婦禁忌、投与中・終了後1週間は避妊必須。機械操作・運転は禁止。吸収効率のため必ず食後に服用すること。重大な副作用に錯乱状態やせん妄がある。"
  },
  {
    "name": "ボルチオキセチン",
    "brand": "トリンテリックス",
    "category": "抗うつ薬",
    "class": "マルチモーダル抗うつ薬",
    "action_type": "抗うつ作用・認知機能改善作用",
    "mechanism": "SERT阻害＋5-HT1A部分作動薬・5-HT1B部分作動薬・5-HT3/7拮抗など多標的（マルチモーダル）。認知機能（記憶・実行機能）への改善効果が示されている",
    "potency": "10mg ≑ IMP 100mg",
    "efficacy_star": 3,
    "placebo_onset": "MADRS −3.5点（プラセボ比）",
    "placebo_sleep": "治療反応率+16%",
    "NNT": 8,
    "duration_hours": "効果発現まで2〜4週間",
    "guideline_rank": "認知機能障害が問題のうつ病。マルチモーダル作用で再発予防",
    "evidence": "Cipriani et al., Lancet 2018; McIntyre et al., Int J Neuropsychopharmacol 2014",
    "caution": "嘔気は頻度多いが一過性。性機能障害はSSRIより少ない。認知機能への改善効果に関するデータが蓄積中"
  },
  {
    "name": "ミルタザピン",
    "brand": "リフレックス／レメロン",
    "category": "抗うつ薬",
    "class": "NaSSA",
    "action_type": "抗うつ作用・鎮静作用・食欲増進作用",
    "mechanism": "α2受容体遮断（NA・5-HT遊離促進）＋5-HT2A/2C・5-HT3・H1受容体遮断（NaSSA）。SSRIと異なる機序で早期に睡眠・食欲が改善",
    "potency": "30mg ≑ IMP 100mg",
    "efficacy_star": 4,
    "placebo_onset": "HAMD −3.0点（プラセボ比）",
    "placebo_sleep": "治療反応率+23%",
    "NNT": 6.5,
    "duration_hours": "効果発現まで1〜2週間（睡眠・食欲改善は比較的早い）",
    "guideline_rank": "不眠・食欲低下・体重減少を伴ううつに。鎮静が強く就寝前投与",
    "evidence": "Cipriani et al., Lancet 2018; Benkert et al., 2006",
    "caution": "体重増加・眠気が強い（H1強遮断）。性機能障害は少ない。食欲低下・不眠を伴ううつ病に特に適している"
  },
  {
    "name": "デュロキセチン",
    "brand": "サインバルタ",
    "category": "抗うつ薬",
    "class": "SNRI",
    "action_type": "抗うつ作用・抗不安作用・鎮痛補助作用",
    "mechanism": "SERT・NET阻害により下行性疼痛抑制系（NA・5-HT系）を賦活。うつ病・GAD・神経障害性疼痛・慢性腰痛に幅広く適応",
    "potency": "40mg ≑ IMP 100mg",
    "efficacy_star": 4,
    "placebo_onset": "HAMD −4.4点（うつ病；プラセボ比）",
    "placebo_sleep": "治療反応率+27%（うつ病）",
    "NNT": 3.7,
    "duration_hours": "効果発現まで2〜4週間",
    "guideline_rank": "うつ病・GAD・糖尿病性神経障害・慢性腰痛にも適応",
    "evidence": "Cipriani et al., Lancet 2018; Hartford et al., 2007（GAD）",
    "caution": "嘔気・血圧上昇。急激な中断は避ける。抗不安薬・神経障害性疼痛カテゴリにも掲載"
  },
  {
    "name": "ベンラファキシン",
    "brand": "エフェクサーSR",
    "category": "抗うつ薬",
    "class": "SNRI",
    "action_type": "抗うつ作用・抗不安作用・鎮痛補助作用",
    "mechanism": "SERT・NET（ノルエピネフリントランスポーター）の両方を阻害。低用量はSERT優位、高用量でNET効果が増強し、鎮痛・抗不安にも作用",
    "potency": "75mg ≑ IMP 100mg",
    "efficacy_star": 4,
    "placebo_onset": "HAMD −2.9点（プラセボ比）",
    "placebo_sleep": "治療反応率+22%",
    "NNT": 6.5,
    "duration_hours": "効果発現まで2〜4週間",
    "guideline_rank": "うつ病・GAD・社交不安。難治例でSNRIに切り替える際に",
    "evidence": "Cipriani et al., Lancet 2018; Davidson et al., J Clin Psychiatry 2004（GAD）",
    "caution": "血圧上昇（特に高用量）。中断症状が強め。嘔気。高用量でNET阻害増強（鎮痛効果増加）"
  },
  {
    "name": "ミルナシプラン",
    "brand": "トレドミン",
    "category": "抗うつ薬",
    "class": "SNRI",
    "action_type": "抗うつ作用・鎮痛補助作用（線維筋痛症）",
    "mechanism": "NET・SERTの両方を阻害（NET優位）。下行性疼痛抑制系への作用が強く、線維筋痛症などの慢性疼痛にも効果的",
    "potency": "50mg ≑ IMP 100mg",
    "efficacy_star": 3,
    "placebo_onset": "HAMD −2.1点（プラセボ比）",
    "placebo_sleep": "治療反応率+16%",
    "NNT": 8,
    "duration_hours": "効果発現まで2〜4週間",
    "guideline_rank": "うつ病GADに適応。慢性疼痛合併例にも選択肢",
    "evidence": "国内臨床試験データ；Arnold et al., Arthritis Rheum 2004（線維筋痛症）",
    "caution": "NET阻害がSERTより強い。排尿困難（男性）。日本での線維筋痛症適応は「トレドミン」"
  },
  {
    "name": "セルトラリン",
    "brand": "ジェイゾロフト",
    "category": "抗うつ薬",
    "class": "SSRI",
    "action_type": "抗うつ作用・抗不安作用・PTSD改善作用",
    "mechanism": "SERT選択的阻害。他SSRIと比べ薬物相互作用が少なく、副作用プロファイルが良好。国際的に最も広く使用されるSSRIの一つ",
    "potency": "50mg ≑ IMP 100mg",
    "efficacy_star": 4,
    "placebo_onset": "HAMD −2.7点（プラセボ比）",
    "placebo_sleep": "治療反応率+20%",
    "NNT": 7,
    "duration_hours": "効果発現まで2〜4週間",
    "guideline_rank": "うつ病・各種不安症の第一選択。妊娠中・産後うつのエビデンスあり",
    "evidence": "Cipriani et al., Lancet 2018（有効性・忍容性バランス最良）",
    "caution": "副作用プロファイルが良好。薬物相互作用が少ない。PTSDにも適応あり。導入初期の不安増強に注意"
  },
  {
    "name": "フルボキサミン",
    "brand": "デプロメール／ルボックス",
    "category": "抗うつ薬",
    "class": "SSRI",
    "action_type": "抗うつ作用・抗強迫作用・抗不安作用",
    "mechanism": "セロトニントランスポーター（SERT）を選択的に阻害し、シナプス間隙のセロトニン濃度を増加。CYP1A2・CYP2C19を強く阻害するため薬物相互作用が多い",
    "potency": "50mg ≑ IMP 100mg",
    "efficacy_star": 3,
    "placebo_onset": "HAMD −2.3点（プラセボ比）",
    "placebo_sleep": "治療反応率+18%",
    "NNT": 7.5,
    "duration_hours": "効果発現まで2〜4週間",
    "guideline_rank": "うつ病・強迫症（OCD）第一選択。CYP1A2阻害に注意",
    "evidence": "Cipriani et al., Lancet 2018（PMID:29477251）",
    "caution": "CYP1A2・CYP2C19を強く阻害（薬物相互作用多）。強迫性障害（OCD）への適応あり。嘔気が出やすい"
  },
  {
    "name": "アリピプラゾール",
    "brand": "エビリファイ",
    "category": "抗うつ薬",
    "class": "非定型抗精神病薬（DSS）",
    "action_type": "抗うつ補助作用（SSRIへの増強）",
    "mechanism": "D2部分作動薬＋5-HT1A部分作動薬・5-HT2A拮抗。抗うつ薬単独不応例の増強療法として使用",
    "potency": "6.5mg ≑ CPZ 100mg",
    "efficacy_star": 4,
    "placebo_onset": "MADRS −3.0点（うつ病補助；プラセボ比）",
    "placebo_sleep": "治療反応率+20%（補助療法）",
    "NNT": 7,
    "duration_hours": "効果発現1〜2週間（補助療法として）",
    "guideline_rank": "代謝副作用が少ない。体重増加・QT延長を避けたい患者に",
    "evidence": "Berman et al., CNS Spectr 2007; Berman et al., J Clin Psychiatry 2009",
    "caution": "アカシジアが多め。体重・代謝への影響は少ない。抗精神病薬（非定型）カテゴリにも掲載"
  },
  {
    "name": "ブレクスピプラゾール",
    "brand": "レキサルティ",
    "category": "抗うつ薬",
    "class": "非定型抗精神病薬（DSS）",
    "action_type": "抗うつ補助作用（SSRIへの増強）",
    "mechanism": "D2部分作動薬（安定した部分作動活性）＋5-HT1A部分作動薬・5-HT2A強力拮抗。アリピプラゾールよりアカシジアが少なく抗うつ補助に使いやすい",
    "potency": "3mg ≑ CPZ 100mg",
    "efficacy_star": 3,
    "placebo_onset": "MADRS −3.0点（うつ病補助；プラセボ比）",
    "placebo_sleep": "治療反応率+15%（補助療法）",
    "NNT": 8,
    "duration_hours": "効果発現1〜2週間（補助療法として）",
    "guideline_rank": "陰性症状・抑うつへの効果。忍容性に優れ認知機能改善の期待",
    "evidence": "Thase et al., J Clin Psychiatry 2015（うつ病補助）",
    "caution": "アカシジアはアリピプラゾールより少ない。体重増加はやや多め。抗精神病薬（非定型）カテゴリにも掲載"
  },
  {
    "name": "アミトリプチリン",
    "brand": "トリプタノール",
    "category": "抗うつ薬",
    "class": "三環系抗うつ薬（TCA）",
    "action_type": "抗うつ作用・鎮痛補助作用・鎮静作用",
    "mechanism": "SERT・NET阻害＋強い抗コリン・H1遮断・α1遮断・Na+チャネル遮断。多面的な作用で神経障害性疼痛にも第一選択薬",
    "potency": "100mg（IMP換算基準薬と同等）",
    "efficacy_star": 4,
    "placebo_onset": "HAMD −2.8点（プラセボ比）",
    "placebo_sleep": "治療反応率+20%",
    "NNT": 7,
    "duration_hours": "効果発現まで2〜4週間（神経痛：1〜2週間）",
    "guideline_rank": "うつ病に適する",
    "evidence": "Cipriani et al., Lancet 2018; Cochrane（神経障害性疼痛 Derry et al. 2012）",
    "caution": "口渇・便秘・尿閉（抗コリン）、眠気（H1遮断）、起立性低血圧（α1遮断）が強い。過量服用で心毒性。神経障害性疼痛カテゴリにも掲載"
  },
  {
    "name": "クロミプラミン",
    "brand": "アナフラニール",
    "category": "抗うつ薬",
    "class": "三環系抗うつ薬（TCA）",
    "action_type": "抗うつ作用・抗強迫作用（OCD）",
    "mechanism": "TCAの中でSERT阻害作用が特に強い。強迫性障害（OCD）に対してSSRIと並ぶ金標準薬。抗コリン・心毒性も伴う",
    "potency": "100mg ≑ IMP 100mg",
    "efficacy_star": 4,
    "placebo_onset": "HAMD −2.8点；Y-BOCS −4.5点（OCD）",
    "placebo_sleep": "治療反応率+22%（うつ病）；OCD反応率+35%",
    "NNT": 6,
    "duration_hours": "効果発現まで2〜4週間",
    "guideline_rank": "うつ病・強迫症（OCD）のTCA。OCD治療に特に有用",
    "evidence": "Cipriani et al., Lancet 2018; DeVeaugh-Geiss et al., J Clin Psychiatry 1989（OCD）",
    "caution": "TCA中で最もSERT選択性が高く、OCD治療に特に有効。抗コリン・心毒性に注意"
  },
  {
    "name": "イミプラミン",
    "brand": "トフラニール",
    "category": "抗うつ薬",
    "class": "三環系抗うつ薬（TCA）",
    "action_type": "抗うつ作用・抗パニック作用",
    "mechanism": "SERT・NET阻害（TCAの代表薬）。抗コリン・H1・α1遮断作用を伴う。パニック障害治療薬として歴史的に重要",
    "potency": "100mg（IMP換算基準薬）",
    "efficacy_star": 3,
    "placebo_onset": "HAMD −2.6点（プラセボ比）",
    "placebo_sleep": "治療反応率+19%",
    "NNT": 7.5,
    "duration_hours": "効果発現まで2〜4週間",
    "guideline_rank": "難治性うつ・夜尿症。相互作用・心毒性モニタリングが必要",
    "evidence": "Cipriani et al., Lancet 2018; Klein 1964（パニック障害の先駆的研究）",
    "caution": "抗コリン副作用・心毒性（QT延長・心室性不整脈）。過量服用リスク。パニック障害・夜尿症にも適応"
  },
  {
    "name": "リチウム",
    "brand": "リーマス",
    "category": "気分安定薬",
    "class": "リチウム塩",
    "action_type": "気分安定作用・抗躁作用・自殺リスク低減作用",
    "mechanism": "グルタミン酸シグナル調節・GSK-3β阻害・イノシトールリン酸代謝阻害など多面的な神経保護・シグナル調節（完全な機序は未解明）。自殺予防効果が唯一強いエビデンスを持つ薬",
    "potency": "換算なし（特殊系）",
    "efficacy_star": 5,
    "placebo_onset": "YMRS −6.0点（躁状態；プラセボ比）",
    "placebo_sleep": "再発リスク−40%（維持療法）",
    "NNT": 5,
    "duration_hours": "半減期20〜24時間（1日2〜3回投与）",
    "guideline_rank": "双極性障害の自殺リスク低減エビデンスあり。血中濃度モニタリング必須",
    "evidence": "Cipriani et al., Lancet 2013; Goodwin et al., JAMA 2016（自殺リスク低減）",
    "caution": "治療域が狭い（0.6〜1.2mEq/L）。腎・甲状腺機能の定期モニタリング必須。NSAIDや利尿薬でリチウム中毒リスク上昇。妊婦は注意"
  },
  {
    "name": "バルプロ酸",
    "brand": "デパケン",
    "category": "気分安定薬",
    "class": "脂肪酸系気分安定薬",
    "action_type": "気分安定作用・抗てんかん作用・抗躁作用",
    "mechanism": "電位依存性Na+チャネル遮断＋GABA分解酵素（GABA-T）阻害によりGABA濃度増加。ヒストン脱アセチル化酵素（HDAC）阻害による遺伝子発現調節も担う",
    "potency": "換算なし（特殊系）",
    "efficacy_star": 4,
    "placebo_onset": "YMRS −8.0点（躁状態；プラセボ比）",
    "placebo_sleep": "躁反応率+40%",
    "NNT": 4.5,
    "duration_hours": "半減期9〜16時間（徐放製剤で1日1〜2回）",
    "guideline_rank": "双極性・てんかん・偏頭痛予防。肝毒性・催奇形性に注意",
    "evidence": "Bowden et al., JAMA 1994（双極性障害）; Cochrane（抗てんかん）",
    "caution": "催奇形性（妊婦禁忌）。体重増加・肝毒性・血小板減少。定期的な血液・肝機能検査が必要。抗てんかん薬カテゴリにも掲載"
  },
  {
    "name": "カルバマゼピン",
    "brand": "テグレトール",
    "category": "気分安定薬",
    "class": "気分安定薬（Na+チャネル遮断薬）",
    "action_type": "気分安定作用・抗てんかん作用・神経痛治療作用",
    "mechanism": "電位依存性Na+チャネルの不活性化状態を安定化させ、神経膜の過剰な興奮を抑制。三叉神経痛の第一選択薬でもある",
    "potency": "換算なし（特殊系）",
    "efficacy_star": 3,
    "placebo_onset": "YMRS −7.0点（躁状態；プラセボ比）",
    "placebo_sleep": "躁反応率+35%",
    "NNT": 5.5,
    "duration_hours": "半減期14〜27時間（自己誘導で短縮）",
    "guideline_rank": "双極性・三叉神経痛。CYP誘導薬で相互作用が多い",
    "evidence": "NICE ガイドライン2014; Cochrane（てんかん・三叉神経痛）",
    "caution": "CYP3A4誘導で薬物相互作用多い。自己誘導で血中濃度が低下。重篤な皮膚副作用（SJS/TEN）のリスクあり。抗てんかん薬・神経障害性疼痛カテゴリにも掲載"
  },
  {
    "name": "ラモトリギン",
    "brand": "ラミクタール",
    "category": "気分安定薬",
    "class": "気分安定薬（グルタミン酸調節薬）",
    "action_type": "気分安定作用（うつ相予防に優れる）・抗てんかん作用",
    "mechanism": "電位依存性Na+チャネル遮断＋グルタミン酸（興奮性神経伝達物質）の過剰放出を抑制。躁状態予防よりうつ相予防に特に優れる",
    "potency": "換算なし（特殊系）",
    "efficacy_star": 4,
    "placebo_onset": "HDRS −2.0点（うつ相予防；プラセボ比）",
    "placebo_sleep": "うつ相再発防止率+35%",
    "NNT": 6,
    "duration_hours": "半減期25〜33時間（1日1〜2回）",
    "guideline_rank": "双極性うつ状態の再発予防に優れる。皮疹（Stevens-Johnson）に注意し緩徐増量",
    "evidence": "Calabrese et al., J Clin Psychiatry 1999; Goodwin et al., J Clin Psychiatry 2004",
    "caution": "重篤な皮疹（SJS）：漸増スケジュールが必須。バルプロ酸との併用で血中濃度上昇。抗てんかん薬カテゴリにも掲載"
  },
  {
    "name": "ドネペジル",
    "brand": "アリセプト",
    "category": "認知症治療薬",
    "class": "ChE阻害薬（AChEI）",
    "action_type": "認知機能改善作用・記憶障害改善作用",
    "mechanism": "AChE（AChE）を可逆的・選択的に阻害し、シナプス間隙のACh濃度を維持して記憶・認知機能を補助",
    "potency": "換算なし（AChEI）",
    "efficacy_star": 3,
    "placebo_onset": "ADAS-cog −2.7点（プラセボ比）",
    "placebo_sleep": "悪化遅延+4〜6ヶ月",
    "NNT": 7,
    "duration_hours": "半減期約70時間（1日1回）",
    "guideline_rank": "アルツハイマー・レビー小体型認知症に。軽度〜重度まで適応",
    "evidence": "Rogers et al., Neurology 1998（PMID:9881220）; Rogers et al., Arch Intern Med 1998",
    "caution": "嘔気・下痢・徐脈。高用量10mgは効果増強だが副作用増加。レビー小体型認知症・パーキンソン病認知症にも適応"
  },
  {
    "name": "リバスチグミン",
    "brand": "イクセロン／リバスタッチ",
    "category": "認知症治療薬",
    "class": "ChE阻害薬（AChEI/BuChEI）",
    "action_type": "認知機能改善作用（特にレビー小体型）・記憶障害改善作用",
    "mechanism": "AChEおよびブチリルChE（BuChE）の両方を擬不可逆的に阻害。脳内でBuChEが増加する進行例に特に有効",
    "potency": "換算なし（AChEI）",
    "efficacy_star": 3,
    "placebo_onset": "ADAS-cog −2.3点（プラセボ比）",
    "placebo_sleep": "悪化遅延+3〜5ヶ月",
    "NNT": 8,
    "duration_hours": "半減期1.5時間（活性代謝物10時間）；パッチ製剤は24時間効果",
    "guideline_rank": "アルツハイマー・パーキンソン認知症に。貼付剤で服薬管理が容易",
    "evidence": "Corey-Bloom et al., Int J Geriatr Psychiatry 1998; PMDA審査資料",
    "caution": "消化器症状が多い（パッチ製剤で軽減可）。パーキンソン病認知症・レビー小体型認知症に特に効果的"
  },
  {
    "name": "ガランタミン",
    "brand": "レミニール",
    "category": "認知症治療薬",
    "class": "ChE阻害薬（AChEI）＋APL",
    "action_type": "認知機能改善作用・注意機能改善作用",
    "mechanism": "AChE阻害＋ニコチン性ACh受容体（nAChR）への正アロステリック調節（APL）によりAChの効果を増強。二重機序が他AChEIと異なる",
    "potency": "換算なし（AChEI）",
    "efficacy_star": 3,
    "placebo_onset": "ADAS-cog −2.5点（プラセボ比）",
    "placebo_sleep": "悪化遅延+4〜5ヶ月",
    "NNT": 7.5,
    "duration_hours": "半減期7〜8時間（徐放製剤で1日1回）",
    "guideline_rank": "アルツハイマー軽度〜中等度。ニコチン性受容体増感作用を持つ",
    "evidence": "Raskind et al., Neurology 2000（PMID:10961583）",
    "caution": "嘔気・嘔吐。徐放製剤で忍容性改善。AChE阻害＋nAChR正アロステリック調節の二重機序"
  },
  {
    "name": "メマンチン",
    "brand": "メマリー",
    "category": "認知症治療薬",
    "class": "NMDA受容体拮抗薬",
    "action_type": "認知機能維持作用（中等度〜重度）・興奮・攻撃性の緩和",
    "mechanism": "NMDA型グルタミン酸受容体の非競合的拮抗薬。グルタミン酸過剰による神経毒性（興奮毒性）を抑制し、正常なシグナル伝達を保護",
    "potency": "換算なし（NMDA系）",
    "efficacy_star": 3,
    "placebo_onset": "SIB +5.7点（重度認知症；プラセボ比）",
    "placebo_sleep": "悪化遅延+4〜8ヶ月",
    "NNT": 9,
    "duration_hours": "半減期60〜100時間（1日1〜2回）",
    "guideline_rank": "中等度〜重度アルツハイマーに。AChEI との併用で相乗効果",
    "evidence": "Reisberg et al., NEJM 2003（PMID:12672860）; Cochrane Review",
    "caution": "眩暈・頭痛・便秘。AChEIとの併用が一般的（中等度〜重度）。腎機能低下時は減量"
  },
  {
    "name": "レカネマブ",
    "brand": "レケンビ",
    "category": "認知症治療薬",
    "class": "抗アミロイドβ抗体（疾患修飾薬）",
    "action_type": "アルツハイマー型認知症の疾患修飾（進行抑制）",
    "mechanism": "脳内アミロイドβ（可溶性プロトフィブリル）に結合してクリアランスを促進。認知症進行を27%遅延",
    "placebo_onset": "CDR-SB悪化抑制 プラセボ比−0.45点（27%遅延）",
    "placebo_sleep": "治療反応率（進行抑制）約27%の差",
    "NNT": 10,
    "efficacy_star": 3,
    "duration_hours": "2週間に1回点滴（t1/2 約5日）",
    "guideline_rank": "MCI〜軽度ADに限定。アミロイド病理を持つ早期例の進行抑制",
    "evidence": "van Dyck CH et al. NEJM 2023（CLARITY AD試験 PMID:36449413）",
    "evidence_url": "https://pubmed.ncbi.nlm.nih.gov/36449413/",
    "caution": "ARIA（アミロイド関連画像異常：脳浮腫・微小出血）に注意。APOE4ホモ接合体はリスク高。MRI定期モニタリング必須。抗凝固薬との併用慎重"
  },
  {
    "name": "オランザピン",
    "brand": "ジプレキサ",
    "category": "双極性障害そう状態",
    "class": "非定型抗精神病薬（MARTA）",
    "action_type": "抗そう作用・抗精神病作用",
    "mechanism": "D2/D3・5-HT2A・H1・M1など多受容体を遮断。そう状態の興奮・精神症状・不眠を迅速に鎮静。最も強力な抗そう効果の1つ",
    "efficacy_star": 5,
    "placebo_onset": "YMRS -8.5点",
    "placebo_sleep": "治療反応率+43%",
    "NNT": 4,
    "onset_time": "数日-1週",
    "duration_hours": "1日1回",
    "guideline_rank": "陽性・陰性症状ともに有効。体重増加・代謝リスクを許容できる例に",
    "evidence": "Cochrane Review（Rendell et al. 2006 PMID:12918000）",
    "evidence_url": "https://pubmed.ncbi.nlm.nih.gov/12918000/",
    "caution": "体重増加・高血糖・代謝異常リスクが高い。高齢者の転倒・誤嚥リスク。急性期後は継続投与の必要性を評価する"
  },
  {
    "name": "クエチアピン（そう状態）",
    "brand": "セロクエル",
    "category": "双極性障害そう状態",
    "class": "非定型抗精神病薬（MARTA）",
    "action_type": "抗そう作用・鎮静作用",
    "mechanism": "D2・5-HT2A・H1・α1など多受容体遮断。強い鎮静作用でそう状態の不眠・興奮を迅速に制御。うつ相にも適応あり",
    "efficacy_star": 4,
    "placebo_onset": "YMRS -6.8点",
    "placebo_sleep": "治療反応率+34%",
    "NNT": 5,
    "onset_time": "数日-1週",
    "duration_hours": "1日2-3回（速放）/ 1日1回（徐放）",
    "guideline_rank": "その疾患の標準的な選択肢",
    "evidence": "Bowden et al., Bipolar Disord 2005（PMID:15669897）",
    "evidence_url": "https://pubmed.ncbi.nlm.nih.gov/15669897/",
    "caution": "強い鎮静・眠気。体重増加・高血糖リスク。QT延長・起立性低血圧。急激な中断で反跳性不眠"
  },
  {
    "name": "アセナピン",
    "brand": "シクレスト",
    "category": "双極性障害そう状態",
    "class": "非定型抗精神病薬（MARTA）",
    "action_type": "抗そう作用",
    "mechanism": "D2/D3・5-HT2A/2B・α2C・H1など多受容体遮断。舌下錠で初回通過効果を回避し速効性が高い",
    "efficacy_star": 3,
    "placebo_onset": "YMRS -6.0点",
    "placebo_sleep": "治療反応率+30%",
    "NNT": 7,
    "onset_time": "数日",
    "duration_hours": "1日2回（舌下錠）",
    "guideline_rank": "舌下投与で剤形の選択肢が増える。体重増加は中程度",
    "evidence": "McIntyre et al., J Affect Disord 2010（PMID:20096936）",
    "evidence_url": "https://pubmed.ncbi.nlm.nih.gov/20096936/",
    "caution": "舌下服用後10分は飲食禁止。口腔内しびれ・感覚異常。体重増加はオランザピンより少ない"
  },
  {
    "name": "リスペリドン",
    "brand": "リスパダール",
    "category": "双極性障害そう状態",
    "class": "非定型抗精神病薬（SDA）",
    "action_type": "抗そう作用・抗精神病作用",
    "mechanism": "D2受容体遮断と5-HT2A受容体遮断のバランス型。そう状態の幻覚・妄想・興奮・攻撃性を改善",
    "efficacy_star": 4,
    "placebo_onset": "YMRS -6.5点",
    "placebo_sleep": "治療反応率+33%",
    "NNT": 6,
    "onset_time": "数日",
    "duration_hours": "1日1-2回",
    "guideline_rank": "非定型の基本薬。幻覚・妄想に有効で剤形豊富（内服・液・注射・デポ）",
    "evidence": "Smulevich et al., Br J Psychiatry 2005（PMID:16135859）",
    "evidence_url": "https://pubmed.ncbi.nlm.nih.gov/16135859/",
    "caution": "D2遮断が強くEPS（錐体外路症状）リスクが高い。高プロラクチン血症・月経異常・性機能障害"
  },
  {
    "name": "アリピプラゾール",
    "brand": "エビリファイ",
    "category": "双極性障害そう状態",
    "class": "非定型抗精神病薬（DSS）",
    "action_type": "抗そう作用（ドパミン安定化）",
    "mechanism": "D2/D3受容体部分作動薬・5-HT1A部分作動薬・5-HT2A拮抗薬。ドパミン過剰を正規化し代謝系副作用が少ない",
    "efficacy_star": 4,
    "placebo_onset": "YMRS -7.0点",
    "placebo_sleep": "治療反応率+37%",
    "NNT": 5,
    "onset_time": "数日-1週",
    "duration_hours": "1日1回",
    "guideline_rank": "代謝副作用が少ない。体重増加・QT延長を避けたい患者に",
    "evidence": "Sachs et al., J Clin Psychiatry 2006（PMID:16669728）",
    "evidence_url": "https://pubmed.ncbi.nlm.nih.gov/16669728/",
    "caution": "体重増加・代謝系副作用は少ない。アカシジア（静座不能）に注意。不眠・活性化症候群が出ることがある"
  },
  {
    "name": "炭酸リチウム",
    "brand": "リーマス",
    "category": "双極性障害そう状態",
    "class": "リチウム塩",
    "action_type": "気分安定作用（そう状態抑制）",
    "mechanism": "イノシトールリン酸代謝抑制・GSK-3β阻害・神経保護など多機序。長年の第一選択薬",
    "efficacy_star": 4,
    "placebo_onset": "YMRS -8.0点",
    "placebo_sleep": "治療反応率+40%",
    "NNT": 5,
    "onset_time": "1-2週",
    "duration_hours": "1日2-3回（血中濃度0.8-1.2 mEq/L）",
    "guideline_rank": "てんかんよりも双極性障害が主適応（抗てんかん薬として使用する場合）",
    "evidence": "Cochrane Review（Cipriani et al. 2013 PMID:31152444）",
    "evidence_url": "https://pubmed.ncbi.nlm.nih.gov/31152444/",
    "caution": "有効治療域が狭く中毒リスク高。腎機能・甲状腺機能の定期モニタリング必須。脱水・NSAIDs・ACE阻害薬で中毒リスク上昇。自殺リスク低減効果あり"
  },
  {
    "name": "バルプロ酸ナトリウム",
    "brand": "デパケン",
    "category": "双極性障害そう状態",
    "class": "脂肪酸系気分安定薬",
    "action_type": "気分安定作用（そう状態抑制）",
    "mechanism": "GABA-T阻害によるGABA活性増強・Na+/T型Caチャネル遮断・HDAC阻害。急性そう状態への即効性あり",
    "efficacy_star": 4,
    "placebo_onset": "YMRS -6.5点",
    "placebo_sleep": "治療反応率+35%",
    "NNT": 6,
    "onset_time": "3-5日",
    "duration_hours": "1日2-3回（血中濃度50-100 microg/mL）",
    "guideline_rank": "その疾患の標準的な選択肢",
    "evidence": "Cochrane Review（Macritchie et al. 2003 PMID:12535506）",
    "evidence_url": "https://pubmed.ncbi.nlm.nih.gov/12535506/",
    "caution": "肝障害・高アンモニア血症・体重増加・催奇形性（妊婦禁忌）。血中濃度モニタリング要。ラモトリギン血中濃度を約2倍に上昇させる"
  },
  {
    "name": "カルバマゼピン",
    "brand": "テグレトール",
    "category": "双極性障害そう状態",
    "class": "気分安定薬（Na+チャネル遮断薬）",
    "action_type": "抗そう作用",
    "mechanism": "Na+チャネル遮断による神経過興奮の抑制。辺縁系に優位に作用しそう状態を抑制",
    "efficacy_star": 3,
    "placebo_onset": "YMRS -5.5点",
    "placebo_sleep": "治療反応率+27%",
    "NNT": 8,
    "onset_time": "1-2週",
    "duration_hours": "1日2-3回（血中濃度4-12 microg/mL）",
    "guideline_rank": "双極性・三叉神経痛。CYP誘導薬で相互作用が多い",
    "evidence": "Vasudev et al., Cochrane Review 2006",
    "evidence_url": null,
    "caution": "多数の薬物相互作用（CYP3A4強力誘導）。SJS（アジア系はHLA-B*1502スクリーニング推奨）。血中濃度モニタリング必須"
  },
  {
    "name": "クエチアピン",
    "brand": "セロクエル",
    "category": "双極性障害うつ状態",
    "class": "非定型抗精神病薬（MARTA）",
    "action_type": "双極うつ状態改善作用",
    "mechanism": "活性代謝産物ノルクエチアピンがノルエピネフリン再取り込みを阻害。5-HT2A遮断・5-HT1A部分作動も寄与。躁転リスクが低い",
    "efficacy_star": 4,
    "placebo_onset": "MADRS -5.2点",
    "placebo_sleep": "治療反応率+23%",
    "NNT": 6,
    "onset_time": "1-2週",
    "duration_hours": "1日1回（就寝前）",
    "guideline_rank": "鎮静・睡眠障害合併例に。代謝影響はオランザピンより少ない",
    "evidence": "Calabrese et al., Am J Psychiatry 2005（PMID:15994719）",
    "evidence_url": "https://pubmed.ncbi.nlm.nih.gov/15994719/",
    "caution": "眠気・体重増加・代謝系副作用。単剤で双極うつに適応あり（抗うつ薬単剤は躁転リスクのため原則回避）"
  },
  {
    "name": "ルラシドン",
    "brand": "ラツーダ",
    "category": "双極性障害うつ状態",
    "class": "非定型抗精神病薬（SDA）",
    "action_type": "双極うつ状態改善作用",
    "mechanism": "D2・5-HT2A拮抗に加え5-HT7拮抗（抗うつへの寄与大）・5-HT1A部分作動。体重・代謝への影響が少ない",
    "efficacy_star": 4,
    "placebo_onset": "MADRS -4.5点",
    "placebo_sleep": "治療反応率+21%",
    "NNT": 7,
    "onset_time": "2-4週",
    "duration_hours": "1日1回（食後必須）",
    "guideline_rank": "代謝への影響が少ない。認知機能改善・食後投与が必須",
    "evidence": "Calabrese et al., Am J Psychiatry 2014（PMID:24170221）",
    "evidence_url": "https://pubmed.ncbi.nlm.nih.gov/24170221/",
    "caution": "空腹時吸収が大幅低下（食後350kcal以上必須）。CYP3A4基質のためグレープフルーツ禁忌。アカシジアに注意"
  },
  {
    "name": "アリピプラゾール（補助）",
    "brand": "エビリファイ",
    "category": "双極性障害うつ状態",
    "class": "非定型抗精神病薬（DSS）",
    "action_type": "双極うつ補助療法",
    "mechanism": "D2/D3部分作動・5-HT1A部分作動による気分安定化。単剤エビデンスは限定的で補助療法として使用",
    "efficacy_star": 2,
    "placebo_onset": "MADRS -2.8点",
    "placebo_sleep": "治療反応率+13%",
    "NNT": 11,
    "onset_time": "2-4週",
    "duration_hours": "1日1回",
    "guideline_rank": "補助的な位置付け",
    "evidence": "Thase et al., J Clin Psychiatry 2008（PMID:18344725）",
    "evidence_url": "https://pubmed.ncbi.nlm.nih.gov/18344725/",
    "caution": "双極うつへの単剤エビデンスは限定的。躁転リスクは低め。アカシジアに注意"
  },
  {
    "name": "ラモトリギン",
    "brand": "ラミクタール",
    "category": "双極性障害うつ状態",
    "class": "気分安定薬（グルタミン酸調節薬）",
    "action_type": "双極うつ相の予防・維持療法",
    "mechanism": "Na+チャネル遮断によるグルタミン酸放出抑制。急性うつよりも長期うつ予防のエビデンスが強い。必ず漸増が必要",
    "efficacy_star": 3,
    "placebo_onset": "MADRS -3.5点",
    "placebo_sleep": "治療反応率+17%",
    "NNT": 9,
    "onset_time": "4-8週（漸増期間含む）",
    "duration_hours": "1日1-2回",
    "guideline_rank": "双極性うつ状態の再発予防に優れる。皮疹（Stevens-Johnson）に注意し緩徐増量",
    "evidence": "Goodwin et al., J Clin Psychiatry 2004（PMID:15096085）",
    "evidence_url": "https://pubmed.ncbi.nlm.nih.gov/15096085/",
    "caution": "SJS・TEN（重篤な皮疹）リスク→漸増プロトコル厳守が必須。バルプロ酸併用で血中濃度が約2倍に（用量半減）。急激な中断禁忌"
  },
  {
    "name": "炭酸リチウム（うつ相）",
    "brand": "リーマス",
    "category": "双極性障害うつ状態",
    "class": "リチウム塩",
    "action_type": "双極うつ改善・自殺リスク低減",
    "mechanism": "GSK-3β阻害・CREB活性化・BDNF増加など多機序。自殺企図を有意に減少させる唯一の気分安定薬",
    "efficacy_star": 3,
    "placebo_onset": "MADRS -3.0点",
    "placebo_sleep": "治療反応率+15%",
    "NNT": 10,
    "onset_time": "2-4週",
    "duration_hours": "1日2-3回（血中濃度0.6-1.0 mEq/L）",
    "guideline_rank": "自殺リスク高例に適する",
    "evidence": "Cipriani et al., Lancet 2013（PMID:23814104）",
    "evidence_url": "https://pubmed.ncbi.nlm.nih.gov/23814104/",
    "caution": "有効治療域が狭く中毒リスク。急性うつへの効果は限定的だが自殺リスク低減効果が特徴的。腎機能低下で蓄積注意"
  },
  {
    "name": "バルプロ酸ナトリウム（うつ相）",
    "brand": "デパケン",
    "category": "双極性障害うつ状態",
    "class": "脂肪酸系気分安定薬",
    "action_type": "双極うつ補助療法",
    "mechanism": "GABA増強・HDAC阻害・神経保護。単剤うつ効果はリチウムより限定的だが混合状態・急速交代型に有用",
    "efficacy_star": 2,
    "placebo_onset": "MADRS -2.5点",
    "placebo_sleep": "治療反応率+12%",
    "NNT": 12,
    "onset_time": "1-2週",
    "duration_hours": "1日2-3回",
    "guideline_rank": "混合状態・急速交代型の場合に代替として検討",
    "evidence": "Davis et al., J Clin Psychiatry 2005（PMID:15780695）",
    "evidence_url": "https://pubmed.ncbi.nlm.nih.gov/15780695/",
    "caution": "単剤でのうつ効果エビデンスは限定的。催奇形性（妊婦禁忌）。ラモトリギン血中濃度を上昇させる"
  },
  {
    "name": "メチルフェニデート",
    "brand": "コンサータ・リタリン",
    "category": "ADHD治療薬",
    "class": "中枢刺激薬（メチルフェニデート）",
    "action_type": "ドパミン・ノルアドレナリン再取り込み阻害（中枢刺激）",
    "mechanism": "ドパミントランスポーター（DAT）・ノルアドレナリントランスポーター（NET）を阻害。前頭前野のドパミン・NA濃度↑で注意力・実行機能を改善",
    "placebo_onset": "ADHD-RS-IV プラセボ比 −10〜14点",
    "placebo_sleep": "治療反応率（CGI改善）65〜75%",
    "NNT": 3,
    "efficacy_star": 5,
    "onset_time": "即放：30〜60分・コンサータ（OROS）：1〜2時間",
    "duration_hours": "コンサータ：12時間・即放：4〜6時間",
    "guideline_rank": "ADHDの最も強いエビデンス。不注意・多動ともに有効な第一選択",
    "evidence": "Cortese S et al. Lancet Psychiatry 2018（ネットワークメタ解析 PMID:30097390）",
    "evidence_url": "https://pubmed.ncbi.nlm.nih.gov/30097390/",
    "caution": "食欲低下・不眠・心拍数↑。依存性あり（向精神薬指定）。心疾患・甲状腺機能亢進は禁忌。成長への影響を定期モニタリング"
  },
  {
    "name": "リスデキサンフェタミン",
    "brand": "ビバンセ",
    "category": "ADHD治療薬",
    "class": "中枢刺激薬（アンフェタミン系）",
    "action_type": "ドパミン・ノルアドレナリン遊離促進＋再取り込み阻害",
    "mechanism": "プロドラッグ（d-アンフェタミンに変換）。ドパミン・ノルアドレナリンのシナプス遊離↑と再取り込み阻害の両方で強力な作用。乱用防止設計",
    "placebo_onset": "ADHD-RS-IV プラセボ比 −12〜16点",
    "placebo_sleep": "治療反応率 70〜80%",
    "NNT": 2.5,
    "efficacy_star": 5,
    "onset_time": "1〜2時間（消化管でアンフェタミンに変換）",
    "duration_hours": "12〜14時間（1日1回朝）",
    "guideline_rank": "乱用リスクが低い設計。コンサータ無効・成人ADHD に",
    "evidence": "Cortese S et al. Lancet Psychiatry 2018（PMID:30097390）",
    "evidence_url": "https://pubmed.ncbi.nlm.nih.gov/30097390/",
    "caution": "食欲低下・不眠・血圧上昇。向精神薬（第一種）。依存性はメチルフェニデートより低い（プロドラッグ設計）。心疾患・高血圧は禁忌"
  },
  {
    "name": "アトモキセチン",
    "brand": "ストラテラ",
    "category": "ADHD治療薬",
    "class": "非刺激薬（NRI）",
    "action_type": "選択的ノルアドレナリン再取り込み阻害（非刺激薬）",
    "mechanism": "前頭前野のNETを選択的阻害→ノルアドレナリン↑→ドパミンも間接的に↑。刺激薬と異なり依存性・乱用リスクが低い",
    "placebo_onset": "ADHD-RS-IV プラセボ比 −7〜10点",
    "placebo_sleep": "治療反応率 50〜60%",
    "NNT": 5,
    "efficacy_star": 3,
    "onset_time": "4〜8週（効果発現が遅い）",
    "duration_hours": "24時間（1日1〜2回）",
    "guideline_rank": "依存性なし・非刺激薬。チック・不安合併・依存症リスクが高い例に",
    "evidence": "Michelson D et al. Am J Psychiatry 2001（PMID:12411225）",
    "evidence_url": "https://pubmed.ncbi.nlm.nih.gov/12411225/",
    "caution": "効果発現まで4〜8週必要。初期に悪心・食欲低下。肝機能障害（まれ）。自殺念慮への注意（小児・青年）。MAO阻害薬と禁忌"
  },
  {
    "name": "グアンファシン",
    "brand": "インチュニブ",
    "category": "ADHD治療薬",
    "class": "非刺激薬（α2A作動薬）",
    "action_type": "前頭前野α2A受容体作動（非刺激薬）",
    "mechanism": "前頭前野のα2A受容体を刺激→cAMP産生↓→K+チャネル開口→神経回路の信号対雑音比↑。衝動性・多動性への効果が特に高い",
    "placebo_onset": "ADHD-RS-IV プラセボ比 −6〜9点",
    "placebo_sleep": "治療反応率 45〜55%（多動性・衝動性に強い）",
    "NNT": 6,
    "efficacy_star": 3,
    "onset_time": "2〜4週（徐放製剤）",
    "duration_hours": "24時間（1日1回就寝前）",
    "guideline_rank": "多動性・衝動性・攻撃性に特に有効。チック合併例にも使用可",
    "evidence": "Sallee FR et al. J Am Acad Child Adolesc Psychiatry 2009（PMID:19106767）",
    "evidence_url": "https://pubmed.ncbi.nlm.nih.gov/19106767/",
    "caution": "眠気・血圧低下・徐脈。急激な中止で反跳性高血圧。アルコールとの相互作用。刺激薬との併用で相乗効果あり"
  },
  {
    "name": "ナルトレキソン",
    "brand": "レビア",
    "category": "アルコール依存症治療薬",
    "class": "オピオイド拮抗薬",
    "action_type": "μ・δ・κオピオイド受容体完全拮抗（断酒・飲酒量低減）",
    "mechanism": "飲酒によるドパミン放出をμ受容体遮断で抑制し、飲酒の快感・渇望を低減。オピオイド依存の維持療法にも使用",
    "placebo_onset": "大量飲酒日数 プラセボ比 −25〜35%",
    "placebo_sleep": "完全断酒率 15〜25%・再飲酒までの期間延長",
    "NNT": 9,
    "efficacy_star": 3,
    "onset_time": "数日〜1週間",
    "duration_hours": "12〜24時間（1日1回または月1回注射剤）",
    "guideline_rank": "飲酒の快感を遮断。「飲酒量低減」「断酒」どちらの目標にも使える",
    "evidence": "Rösner S et al. Cochrane 2010（PMID:21154349）",
    "evidence_url": "https://pubmed.ncbi.nlm.nih.gov/21154349/",
    "caution": "服薬中にオピオイド系薬（鎮痛薬など）が無効になる。急性肝炎・重篤な肝障害は禁忌。悪心・頭痛（初期）。断酒してから服用開始"
  },
  {
    "name": "ナルメフェン",
    "brand": "セリンクロ",
    "category": "アルコール依存症治療薬",
    "class": "オピオイド部分拮抗薬",
    "action_type": "μ・δ受容体拮抗・κ受容体部分作動（飲酒量低減）",
    "mechanism": "飲酒前に服用し飲酒の快感を減弱させる「必要時服用」型。断酒を目標としない飲酒量低減アプローチ（ハームリダクション）",
    "placebo_onset": "大量飲酒日数 プラセボ比 −40〜50%",
    "placebo_sleep": "大量飲酒日数ゼロ達成率 プラセボ比 +15〜20%",
    "NNT": 7,
    "efficacy_star": 4,
    "onset_time": "飲酒1〜2時間前に服用（必要時）",
    "duration_hours": "12〜24時間（飲酒しない日は服用不要）",
    "guideline_rank": "断酒を目標としないハームリダクション型。飲酒前に服用する必要時型",
    "evidence": "Mann K et al. Eur Neuropsychopharmacol 2013（ESENSE試験 PMID:23562264）",
    "evidence_url": "https://pubmed.ncbi.nlm.nih.gov/23562264/",
    "caution": "悪心・めまい・不眠（服用開始初期）。断酒目標でない点が他薬と異なる。肝障害・腎障害で慎重使用"
  },
  {
    "name": "アカンプロサート",
    "brand": "レグテクト",
    "category": "アルコール依存症治療薬",
    "class": "GABA調節薬（断酒補助）",
    "action_type": "GABA-A受容体正調節・グルタミン酸（NMDA）過活動抑制",
    "mechanism": "飲酒中断後のグルタミン酸過活動（離脱状態）を抑制して渇望・不快感を軽減。断酒後に開始する維持療法薬",
    "placebo_onset": "完全断酒率 プラセボ比 +10〜15%（6〜12カ月）",
    "placebo_sleep": "断酒継続期間延長・再飲酒率↓",
    "NNT": 9,
    "efficacy_star": 3,
    "onset_time": "断酒後5日以内に開始（離脱安定後）",
    "duration_hours": "24時間（1日3回食後）",
    "guideline_rank": "断酒後の離脱渇望を抑制。腎機能正常例の断酒維持に",
    "evidence": "Rösner S et al. Cochrane 2010（PMID:20824837）",
    "evidence_url": "https://pubmed.ncbi.nlm.nih.gov/20824837/",
    "caution": "腎排泄のため腎機能低下例は禁忌（CCr<30）。下痢・悪心（初期）。ナルトレキソンとの併用で相乗効果の報告あり"
  },
  {
    "name": "ジスルフィラム",
    "brand": "ノックビン",
    "category": "アルコール依存症治療薬",
    "class": "アルデヒド脱水素酵素阻害薬",
    "action_type": "ALDH2阻害→アセトアルデヒド蓄積による嫌悪反応（抑止療法）",
    "mechanism": "アルコール代謝酵素ALDH2を阻害。飲酒するとアセトアルデヒドが蓄積→顔面紅潮・頭痛・嘔吐・動悸→飲酒抑止",
    "placebo_onset": "飲酒抑止効果（服薬コンプライアンス依存）",
    "placebo_sleep": "断酒率 確認服薬で向上（ナルトレキソンより依存）",
    "NNT": 8,
    "efficacy_star": 3,
    "onset_time": "服薬後12時間以内に飲酒で反応",
    "duration_hours": "効果持続：最終服用から1〜2週間",
    "guideline_rank": "飲酒への嫌悪条件付け。確認服薬が可能で強い意志がある例に",
    "evidence": "Skinner MD et al. PLOS ONE 2014（PMID:24520330）",
    "evidence_url": "https://pubmed.ncbi.nlm.nih.gov/24520330/",
    "caution": "服薬中の飲酒は危険（重篤な心血管反応）。アルコール含有製品（うがい薬・香水など）も禁忌。肝障害・心疾患は禁忌。確認服薬が効果の鍵"
  },
  {
    "name": "シアナミド",
    "brand": "シアナマイド",
    "category": "アルコール依存症治療薬",
    "class": "シアナミド系",
    "action_type": "ALDH阻害（ジスルフィラムと同機序・速効・短時間）",
    "mechanism": "ALDH1・2を阻害しアセトアルデヒド蓄積を引き起こす。ジスルフィラムより作用持続が短く（12時間）、飲酒前投与で管理しやすい",
    "placebo_onset": "飲酒抑止効果（確認服薬で高い）",
    "placebo_sleep": "断酒率（確認服薬群）で良好",
    "NNT": 8,
    "efficacy_star": 3,
    "onset_time": "服薬後1〜3時間で飲酒反応",
    "duration_hours": "効果持続：約12時間（ジスルフィラムより短い）",
    "guideline_rank": "ジスルフィラムと同機序で短時間型。朝の確認服薬として日本で広用",
    "evidence": "添付文書・国内臨床経験",
    "evidence_url": null,
    "caution": "服薬中の飲酒は危険。肝障害に注意（定期肝機能検査）。ジスルフィラムと比較して甲状腺抑制作用が強い。確認服薬が必須"
  },
  {
    "name": "バレニクリン",
    "brand": "チャンピックス",
    "category": "禁煙補助薬",
    "class": "α4β2ニコチン受容体部分作動薬",
    "action_type": "ニコチン性ACh受容体α4β2の部分作動（禁煙補助）",
    "mechanism": "α4β2受容体を部分刺激→喫煙渇望・離脱症状を軽減。同時に完全作動を阻害→喫煙しても満足感が得られにくくなる",
    "placebo_onset": "禁煙成功率（9〜24週）約33〜44%",
    "placebo_sleep": "プラセボ比 禁煙率 OR 3.1〜3.6（最も高いエビデンス）",
    "NNT": 5,
    "efficacy_star": 5,
    "onset_time": "禁煙予定日1週間前から開始",
    "duration_hours": "24時間（1日2回・12週間標準）",
    "guideline_rank": "禁煙補助薬として最も有効。渇望と喫煙満足感の両方を抑制",
    "evidence": "Cahill K et al. Cochrane 2016（PMID:27158893）",
    "evidence_url": "https://pubmed.ncbi.nlm.nih.gov/27158893/",
    "caution": "悪心（最多副作用・食後服用で軽減）。うつ・自殺念慮の報告（精神疾患既往は慎重）。2025年現在チャンピックスは供給停止中・後発品あり"
  },
  {
    "name": "ニコチンパッチ",
    "brand": "ニコチネルTTS・ニコデルム",
    "category": "禁煙補助薬",
    "class": "ニコチン代替療法（経皮）",
    "action_type": "ニコチン補充による離脱症状・渇望軽減",
    "mechanism": "経皮ニコチンで血中ニコチン濃度を一定に保ち、禁煙時の離脱症状（イライラ・集中力低下・体重増加）を軽減。依存性は喫煙より大幅に低い",
    "placebo_onset": "禁煙成功率（6カ月）約17〜18%",
    "placebo_sleep": "プラセボ比 禁煙率 OR 1.8〜2.0",
    "NNT": 11,
    "efficacy_star": 3,
    "onset_time": "貼付後2〜4時間（血中濃度安定）",
    "duration_hours": "24時間（毎日貼り替え・8〜12週間）",
    "guideline_rank": "OTC入手可能。1日1枚交換でニコチンを安定補充。手軽な導入に",
    "evidence": "Stead LF et al. Cochrane 2012（PMID:23152200）",
    "evidence_url": "https://pubmed.ncbi.nlm.nih.gov/23152200/",
    "caution": "皮膚刺激・かぶれ（貼付部位を毎日変える）。心疾患急性期は慎重。就寝中は外しても可（不眠・悪夢の場合）。OTCで入手可能"
  },
  {
    "name": "ニコチンガム",
    "brand": "ニコレット",
    "category": "禁煙補助薬",
    "class": "ニコチン代替療法（口腔内）",
    "action_type": "ニコチン補充（口腔粘膜吸収・必要時使用）",
    "mechanism": "喫煙渇望が生じたときに噛んで使用する「必要時型NRT」。パッチより血中濃度の上昇が速く、急性渇望への対応に優れる",
    "placebo_onset": "禁煙成功率（6カ月）約17%",
    "placebo_sleep": "プラセボ比 禁煙率 OR 1.5〜1.8（パッチとの併用でさらに向上）",
    "NNT": 12,
    "efficacy_star": 3,
    "onset_time": "噛み始め後5〜10分（口腔粘膜吸収）",
    "duration_hours": "30分（1回使用）・1日最大24個まで",
    "guideline_rank": "OTC入手可能。急性渇望のときだけ使う頓服型。パッチとの併用で効果増",
    "evidence": "Stead LF et al. Cochrane 2012（PMID:23152200）",
    "evidence_url": "https://pubmed.ncbi.nlm.nih.gov/23152200/",
    "caution": "飲食後15分は使用しない（吸収↓）。「チュー＆パーク法」で正しく使用する必要あり。顎関節症に注意。OTCで入手可能"
  }
]